lollms/__init__.py
lollms/app.py
lollms/binding.py
lollms/client_session.py
lollms/code_parser.py
lollms/com.py
lollms/config.py
lollms/data.py
lollms/extension.py
lollms/function_call.py
lollms/generation.py
lollms/helpers.py
lollms/internet.py
lollms/main_config.py
lollms/media.py
lollms/paths.py
lollms/personality.py
lollms/security.py
lollms/stt.py
lollms/tasks.py
lollms/terminal.py
lollms/tti.py
lollms/ttm.py
lollms/tts.py
lollms/types.py
lollms/utilities.py
lollms/configs/config.yaml
lollms/functions/__init__.py
lollms/functions/bibliography.py
lollms/functions/calculator.py
lollms/functions/file_manipulation.py
lollms/functions/generate_image.py
lollms/functions/list_personalities.py
lollms/functions/markdown2latex.py
lollms/functions/music_gen.py
lollms/functions/peripherals.py
lollms/functions/roll_a_dice.py
lollms/functions/search.py
lollms/functions/select_image_file.py
lollms/functions/story_writing.py
lollms/functions/summary.py
lollms/functions/summon_personality.py
lollms/functions/take_a_photo.py
lollms/functions/take_screen_shot.py
lollms/functions/timers.py
lollms/functions/analyze_code/__init__.py
lollms/functions/analyze_code/add_code_to_file.py
lollms/functions/analyze_code/add_function_to_file.py
lollms/functions/analyze_code/create_project_database.py
lollms/functions/analyze_code/git_commit.py
lollms/functions/analyze_code/git_pull.py
lollms/functions/analyze_code/list_classes.py
lollms/functions/analyze_code/list_files.py
lollms/functions/analyze_code/retreive_information_for_task.py
lollms/functions/analyze_code/retrieve_classes_from_project.py
lollms/functions/analyze_code/search_class_in_project.py
lollms/functions/analyze_code/update_class_in_file.py
lollms/functions/analyze_code/update_function_in_file.py
lollms/functions/tts/__init__.py
lollms/functions/tts/read_text.py
lollms/functions/tts/read_text_from_file.py
lollms/functions/web/__init__.py
lollms/functions/web/google_search.py
lollms/functions/youtube/__init__.py
lollms-9.5.1.dist-info/LICENSE
lollms-9.5.1.dist-info/METADATA
lollms-9.5.1.dist-info/WHEEL
lollms-9.5.1.dist-info/entry_points.txt
lollms-9.5.1.dist-info/top_level.txt
lollms-9.5.1.dist-info/RECORD
