Metadata-Version: 2.1
Name: lollms
Version: 9.5.1
Summary: A python library for AI personality definition
Home-page: https://github.com/ParisNeo/lollms
Author: Saifeddine ALOUI (ParisNeo)
Author-email: parisneo_ai@gmail.com
Classifier: Programming Language :: Python :: 3.11
Classifier: License :: OSI Approved :: Apache Software License
Classifier: Operating System :: OS Independent
License-File: LICENSE
Requires-Dist: tqdm
Requires-Dist: pyyaml
Requires-Dist: Pillow
Requires-Dist: wget
Requires-Dist: setuptools
Requires-Dist: requests
Requires-Dist: safe-store
Requires-Dist: pipmaster
Requires-Dist: ascii-colors >=0.1.3
Requires-Dist: beautifulsoup4
Requires-Dist: autopep8
Requires-Dist: fastapi
Requires-Dist: uvicorn
Requires-Dist: python-multipart
Requires-Dist: python-socketio
Requires-Dist: python-socketio[client]
Requires-Dist: python-socketio[asyncio_client]
Provides-Extra: dev
Requires-Dist: tqdm ; extra == 'dev'
Requires-Dist: pyyaml ; extra == 'dev'
Requires-Dist: Pillow ; extra == 'dev'
Requires-Dist: wget ; extra == 'dev'
Requires-Dist: setuptools ; extra == 'dev'
Requires-Dist: requests ; extra == 'dev'
Requires-Dist: safe-store ; extra == 'dev'
Requires-Dist: ascii-colors >=0.1.3 ; extra == 'dev'
Requires-Dist: autopep8 ; extra == 'dev'
Requires-Dist: fastapi ; extra == 'dev'
Requires-Dist: uvicorn ; extra == 'dev'
Requires-Dist: python-multipart ; extra == 'dev'
Requires-Dist: python-socketio ; extra == 'dev'
Requires-Dist: python-socketio[client] ; extra == 'dev'
Requires-Dist: python-socketio[asyncio_client] ; extra == 'dev'
